link_shortly-0.0.7.dist-info/licenses/LICENSE
shortly/__init__.py
shortly/errors.py
shortly/shortly.py
shortly/utils.py
link_shortly-0.0.7.dist-info/METADATA
link_shortly-0.0.7.dist-info/WHEEL
link_shortly-0.0.7.dist-info/top_level.txt
link_shortly-0.0.7.dist-info/RECORD
