Metadata-Version: 2.4
Name: link-shortly
Version: 0.0.7
Summary: Link-Shortly is a simple Python library to shorten links using the Link-Shortly API or compatible services
Author-email: rkndeveloper <vardhacopyrightteam@gmail.com>
License: MIT
Project-URL: Homepage, https://github.com/RknDeveloper/link-shortly
Project-URL: Documentation, https://github.com/RknDeveloper/link-shortly#readme
Project-URL: Source, https://github.com/RknDeveloper/link-shortly
Project-URL: Tracker, https://github.com/RknDeveloper/link-shortly/issues
Project-URL: Changelog, https://github.com/RknDeveloper/link-shortly/releases
Keywords: link-shortener,url-shortener,api-wrapper,tinyurl,bitly,ouo.io,adlinkfy,shareus.io,link-shortly
Classifier: Programming Language :: Python :: 3
Classifier: Programming Language :: Python :: 3.6
Classifier: Programming Language :: Python :: 3.7
Classifier: Programming Language :: Python :: 3.8
Classifier: Programming Language :: Python :: 3.9
Classifier: Programming Language :: Python :: 3.10
Classifier: Programming Language :: Python :: 3.11
Classifier: Programming Language :: Python :: 3.12
Classifier: Operating System :: OS Independent
Classifier: Intended Audience :: Developers
Classifier: Topic :: Software Development :: Libraries :: Python Modules
Classifier: Topic :: Internet :: WWW/HTTP
Requires-Python: >=3.6
License-File: LICENSE
Requires-Dist: aiohttp>=3.12.15
Dynamic: license-file
